langsmart_bigtool-0.1.0.dist-info/METADATA
langsmart_bigtool-0.1.0.dist-info/WHEEL
langsmart_bigtool-0.1.0.dist-info/entry_points.txt
langsmart_bigtool-0.1.0.dist-info/licenses/LICENSE
langsmart_bigtool/__init__.py
langsmart_bigtool/agent.py
langsmart_bigtool/utils.py
langsmart_bigtool-0.1.0.dist-info/RECORD
