Metadata-Version: 2.1
Name: langsmart-bigtool
Version: 0.1.0
Summary: A LangGraph agent that uses a two-step process to first select a small subset of tools from a very large collection before executing the user's query.
Author-Email: Paul Okafor <acobapaul@gmail.com>
License: MIT License
Classifier: Programming Language :: Python :: 3
Classifier: License :: OSI Approved :: MIT License
Classifier: Operating System :: OS Independent
Classifier: Intended Audience :: Developers
Classifier: Topic :: Scientific/Engineering :: Artificial Intelligence
Classifier: Topic :: Software Development :: Libraries :: Python Modules
Project-URL: Homepage, https://github.com/obinopaul/langsmart-bigtool
Requires-Python: >=3.10
Requires-Dist: langgraph>=0.5.0
Requires-Dist: trustcall>=0.0.39
Requires-Dist: langchain-core>=0.3.66
Requires-Dist: langchain>=0.3.26
Requires-Dist: langchain-openai>=0.2.0
Requires-Dist: pydantic>=2.0
Requires-Dist: python-dotenv>=1.0.0
